ktio/__init__.py
ktio/ktio.py
ktio-0.1.dist-info/DESCRIPTION.rst
ktio-0.1.dist-info/METADATA
ktio-0.1.dist-info/RECORD
ktio-0.1.dist-info/WHEEL
ktio-0.1.dist-info/metadata.json
ktio-0.1.dist-info/top_level.txt
